aiosumma/__init__.py
aiosumma/cli.py
aiosumma/client.py
aiosumma/proto/__init__.py
aiosumma/proto/consumer_service_pb2.py
aiosumma/proto/consumer_service_pb2.pyi
aiosumma/proto/consumer_service_pb2_grpc.py
aiosumma/proto/dag_pb_pb2.py
aiosumma/proto/dag_pb_pb2.pyi
aiosumma/proto/dag_pb_pb2_grpc.py
aiosumma/proto/index_service_pb2.py
aiosumma/proto/index_service_pb2.pyi
aiosumma/proto/index_service_pb2_grpc.py
aiosumma/proto/public_service_pb2.py
aiosumma/proto/public_service_pb2.pyi
aiosumma/proto/public_service_pb2_grpc.py
aiosumma/proto/query_pb2.py
aiosumma/proto/query_pb2.pyi
aiosumma/proto/query_pb2_grpc.py
aiosumma/proto/reflection_service_pb2.py
aiosumma/proto/reflection_service_pb2.pyi
aiosumma/proto/reflection_service_pb2_grpc.py
aiosumma/proto/search_service_pb2.py
aiosumma/proto/search_service_pb2.pyi
aiosumma/proto/search_service_pb2_grpc.py
aiosumma/proto/unixfs_pb2.py
aiosumma/proto/unixfs_pb2.pyi
aiosumma/proto/unixfs_pb2_grpc.py
aiosumma/proto/utils_pb2.py
aiosumma/proto/utils_pb2.pyi
aiosumma/proto/utils_pb2_grpc.py
aiosumma-2.48.0.dist-info/METADATA
aiosumma-2.48.0.dist-info/WHEEL
aiosumma-2.48.0.dist-info/entry_points.txt
aiosumma-2.48.0.dist-info/top_level.txt
aiosumma-2.48.0.dist-info/RECORD
