Metadata-Version: 2.2
Name: aiosumma
Version: 2.48.0
Summary: Async client for Summa Search
Author-email: Pasha Podolsky <ppodolsky@me.com>
Project-URL: Homepage, https://github.com/izihawa/aiosumma
Project-URL: Documentation, https://izihawa.github.io/summa
Classifier: Programming Language :: Python :: 3.8
Classifier: Topic :: Internet :: WWW/HTTP :: Indexing/Search
Requires-Python: >=3.8
Requires-Dist: aiogrpcclient>=1.3.5
Requires-Dist: fire>=0.3.1
Requires-Dist: izihawa_utils
Requires-Dist: orjson>=3.6.8
Requires-Dist: protobuf>=5.29.3
Requires-Dist: termcolor>=1.1.0
